risk_mirror/__init__.py
risk_mirror/cli.py
risk_mirror/client.py
risk_mirror/types.py
risk_mirror-1.0.2.dist-info/METADATA
risk_mirror-1.0.2.dist-info/WHEEL
risk_mirror-1.0.2.dist-info/entry_points.txt
risk_mirror-1.0.2.dist-info/top_level.txt
risk_mirror-1.0.2.dist-info/RECORD
