Metadata-Version: 2.1
Name: risk-mirror
Version: 1.0.2
Summary: Deterministic AI Safety Toolkit - Python SDK & CLI
Home-page: https://github.com/myProjectsRavi/risk-mirror-core
Author: RTN Labs
Author-email: support@risk-mirror.com
License: UNKNOWN
Keywords: ai-safety,pii,secrets,prompt-security,deterministic,cli
Platform: UNKNOWN
Classifier: Development Status :: 5 - Production/Stable
Classifier: Intended Audience :: Developers
Classifier: License :: OSI Approved :: MIT License
Classifier: Operating System :: OS Independent
Classifier: Programming Language :: Python :: 3
Classifier: Programming Language :: Python :: 3.8
Classifier: Programming Language :: Python :: 3.9
Classifier: Programming Language :: Python :: 3.10
Classifier: Programming Language :: Python :: 3.11
Classifier: Programming Language :: Python :: 3.12
Classifier: Topic :: Security
Classifier: Topic :: Software Development :: Libraries :: Python Modules
Requires-Python: >=3.8
Provides-Extra: dev
Requires-Dist: pytest ; extra == 'dev'
Requires-Dist: pytest-cov ; extra == 'dev'
Requires-Dist: mypy ; extra == 'dev'
